pyjabber/__init__.py
pyjabber/__main__.py
pyjabber/init_utils.py
pyjabber/metadata.py
pyjabber/server.py
pyjabber/server_parameters.py
pyjabber/workers.py
pyjabber/config/config.yaml
pyjabber/db/__init__.py
pyjabber/db/database.py
pyjabber/db/model.py
pyjabber/features/InBandRegistration.py
pyjabber/features/ResourceBinding.py
pyjabber/features/SASLFeature.py
pyjabber/features/StartTLSFeature.py
pyjabber/features/StreamFeature.py
pyjabber/features/__init__.py
pyjabber/features/feature_utils/RosterUtils.py
pyjabber/features/feature_utils/__init__.py
pyjabber/features/presence/PresenceFeature.py
pyjabber/features/presence/__init__.py
pyjabber/network/CertGenerator.py
pyjabber/network/ConnectionManager.py
pyjabber/network/StreamAlivenessMonitor.py
pyjabber/network/XMLParser.py
pyjabber/network/XMLProtocol.py
pyjabber/network/__init__.py
pyjabber/network/certs/ca_cert.pem
pyjabber/network/certs/ca_key.pem
pyjabber/network/server/__init__.py
pyjabber/network/server/incoming/XMLServerIncomingParser.py
pyjabber/network/server/incoming/XMLServerIncomingProtocol.py
pyjabber/network/server/incoming/__init__.py
pyjabber/network/server/outcoming/XMLServerOutcomingParser.py
pyjabber/network/server/outcoming/XMLServerOutcomingProtocol.py
pyjabber/network/server/outcoming/__init__.py
pyjabber/plugins/PluginManager.py
pyjabber/plugins/__init__.py
pyjabber/plugins/roster/Roster.py
pyjabber/plugins/roster/__init__.py
pyjabber/plugins/xep_0004/__init__.py
pyjabber/plugins/xep_0004/field.py
pyjabber/plugins/xep_0004/xep_0004.py
pyjabber/plugins/xep_0030/__init__.py
pyjabber/plugins/xep_0030/xep_0030.py
pyjabber/plugins/xep_0060/__init__.py
pyjabber/plugins/xep_0060/enum.py
pyjabber/plugins/xep_0060/error.py
pyjabber/plugins/xep_0060/xep_0060.py
pyjabber/plugins/xep_0199/__init__.py
pyjabber/plugins/xep_0199/xep_0199.py
pyjabber/stanzas/IQ.py
pyjabber/stanzas/Message.py
pyjabber/stanzas/Presence.py
pyjabber/stanzas/__init__.py
pyjabber/stanzas/error/StanzaError.py
pyjabber-0.2.8.dist-info/licenses/AUTHORS.rst
pyjabber-0.2.8.dist-info/licenses/LICENSE
pyjabber-0.2.8.dist-info/METADATA
pyjabber-0.2.8.dist-info/WHEEL
pyjabber-0.2.8.dist-info/entry_points.txt
pyjabber-0.2.8.dist-info/top_level.txt
pyjabber-0.2.8.dist-info/RECORD
