Metadata-Version: 2.4
Name: pyjabber
Version: 0.2.8
Summary: A Python XMPP server
Home-page: https://github.com/DinoThor/PyJabber
Author: Aarón Raya Lopez, Manel Soler Sanz
Author-email: aaron.raya.lopez@gmail.com
Classifier: Programming Language :: Python :: 3
Classifier: License :: OSI Approved :: MIT License
Classifier: Operating System :: OS Independent
Requires-Python: >=3.8
License-File: LICENSE
License-File: AUTHORS.rst
Requires-Dist: aiohttp==3.10.4
Requires-Dist: alembic~=1.14.1
Requires-Dist: bcrypt==4.3.0
Requires-Dist: click==8.1.7
Requires-Dist: cryptography==43.0.1
Requires-Dist: loguru==0.7.2
Requires-Dist: pyyaml~=6.0.2
Requires-Dist: SQLAlchemy==2.0.40
Requires-Dist: uvloop==0.21.0; sys_platform != "win32"
Requires-Dist: winloop==0.1.8; sys_platform == "win32"
Dynamic: author
Dynamic: author-email
Dynamic: classifier
Dynamic: description
Dynamic: description-content-type
Dynamic: home-page
Dynamic: license-file
Dynamic: requires-dist
Dynamic: requires-python
Dynamic: summary
